CHANGES
LICENSE
MANIFEST.in
README
setup.py
django_websocket/__init__.py
django_websocket/decorators.py
django_websocket/middleware.py
django_websocket/websocket.py
django_websocket.egg-info/PKG-INFO
django_websocket.egg-info/SOURCES.txt
django_websocket.egg-info/dependency_links.txt
django_websocket.egg-info/requires.txt
django_websocket.egg-info/top_level.txt
django_websocket.egg-info/zip-safe
django_websocket/management/__init__.py
django_websocket/management/commands/__init__.py
django_websocket/management/commands/runserver.py
django_websocket_tests/__init__.py
django_websocket_tests/manage.py
django_websocket_tests/models.py
django_websocket_tests/runtests.py
django_websocket_tests/settings.py
django_websocket_tests/tests.py
django_websocket_tests/utils.py
examples/__init__.py
examples/manage.py
examples/settings.py
examples/urls.py
examples/templates/index.html